crmark/__init__.py
crmark/crmark.py
crmark/compressor/__init__.py
crmark/compressor/arithmeticcoder.py
crmark/compressor/rdh.py
crmark/compressor/utils.py
crmark/compressor/utils_compressors.py
crmark/nets/__init__.py
crmark/nets/nets.py
crmark-1.1.1.dist-info/licenses/LICENSE
crmark-1.1.1.dist-info/METADATA
crmark-1.1.1.dist-info/WHEEL
crmark-1.1.1.dist-info/top_level.txt
crmark-1.1.1.dist-info/RECORD
