Metadata-Version: 2.4
Name: crmark
Version: 1.1.1
Summary: A robust reversible watermarking method that can robustly extract the watermark in lossy channels and perfectly recover both the cover image and the watermark in lossless channels.
Home-page: https://github.com/chenoly/crmark
Author: chenoly
Author-email: chenoly@outlook.com
Project-URL: Bug Reports, https://github.com/chenoly/crmark/issues
Project-URL: Source, https://github.com/chenoly/crmark
Project-URL: Documentation, https://crmark.readthedocs.io
Keywords: robust reversible watermarking
Classifier: Development Status :: 3 - Alpha
Classifier: Intended Audience :: Science/Research
Classifier: Intended Audience :: Developers
Classifier: Topic :: Scientific/Engineering :: Image Processing
Classifier: Topic :: Security :: Cryptography
Classifier: License :: OSI Approved :: MIT License
Classifier: Programming Language :: Python :: 3
Classifier: Programming Language :: Python :: 3.7
Classifier: Programming Language :: Python :: 3.8
Classifier: Programming Language :: Python :: 3.9
Classifier: Programming Language :: Python :: 3.10
Classifier: Programming Language :: Python :: 3.11
Classifier: Operating System :: OS Independent
Requires-Python: >=3.7
License-File: LICENSE
Requires-Dist: numpy>=1.21.0
Requires-Dist: torch>=1.10.0
Requires-Dist: Pillow>=8.0.0
Requires-Dist: lpips>=0.1.4
Requires-Dist: bchlib>=2.1.3
Requires-Dist: kornia>=0.6.0
Requires-Dist: tqdm>=4.62.0
Requires-Dist: requests>=2.32.3
Requires-Dist: torchvision>=0.11.0
Requires-Dist: scipy>=1.7.0
Dynamic: author
Dynamic: author-email
Dynamic: classifier
Dynamic: description
Dynamic: description-content-type
Dynamic: home-page
Dynamic: keywords
Dynamic: license-file
Dynamic: project-url
Dynamic: requires-dist
Dynamic: requires-python
Dynamic: summary
